<screen position="360,150" size="560,400">
	<widget name="about" position="10,10" size="460,360" font="Regular;15"/>
	<widget name="rytec_pix" position="480,200" size="70,70"/>
	<widget name="krkadoni_pix" position="480,290" size="70,22"/>
	<widget name="key_red" position="0,360" size="140,40" valign="center" halign="center" zPosition="5" transparent="1" foregroundColor="white" font="Regular;18"/>
	<widget name="key_green" position="140,360" size="140,40" valign="center" halign="center" zPosition="5" transparent="1" foregroundColor="white" font="Regular;18"/>
	<widget name="key_yellow" position="280,360" size="140,40" valign="center" halign="center" zPosition="5" transparent="1" foregroundColor="white" font="Regular;18"/>
	<widget name="key_blue" position="420,360" size="140,40" valign="center" halign="center" zPosition="5" transparent="1" foregroundColor="white" font="Regular;18"/>
	<ePixmap name="red" pixmap="skin_default/buttons/red.png" position="0,360" size="140,40" zPosition="4" transparent="1" alphatest="on"/>
	<ePixmap name="green" pixmap="skin_default/buttons/green.png" position="140,360" size="140,40" zPosition="4" transparent="1" alphatest="on"/>
	<ePixmap name="yellow" pixmap="skin_default/buttons/yellow.png" position="280,360" size="140,40" zPosition="4" transparent="1" alphatest="on"/>
	<ePixmap name="blue" pixmap="skin_default/buttons/blue.png" position="420,360" size="140,40" zPosition="4" transparent="1" alphatest="on"/>
</screen>